MANIFEST.in
README.rst
setup.cfg
setup.py
tec/__init__.py
tec.ic.ia.pc1.g05.egg-info/PKG-INFO
tec.ic.ia.pc1.g05.egg-info/SOURCES.txt
tec.ic.ia.pc1.g05.egg-info/dependency_links.txt
tec.ic.ia.pc1.g05.egg-info/requires.txt
tec.ic.ia.pc1.g05.egg-info/top_level.txt
tec/ic/__init__.py
tec/ic/ia/__init__.py
tec/ic/ia/p1/__init__.py
tec/ic/ia/p1/arbol.py
tec/ic/ia/p1/arboldecision.py
tec/ic/ia/p1/g05.py
tec/ic/ia/p1/kd_tree.py
tec/ic/ia/p1/pc1.py
tec/ic/ia/p1/pruebas_unitarias.py
tec/ic/ia/p1/test_kd_tree.py
tec/ic/ia/pc1/__init__.py
tec/ic/ia/pc1/g05.py
tec/ic/ia/pc1/unittests.py