Metadata-Version: 1.0
Name: tec.ic.ia.pc1.g05
Version: 8.1.0
Summary: g
Home-page: UNKNOWN
Author: JoseMora/DylanRodriguez/KarinaZeledon
Author-email: UNKNOWN
License: UNKNOWN
Platform: UNKNOWN
